neil_vst_gui/__init__.py
neil_vst_gui/job.py
neil_vst_gui/main.py
neil_vst_gui/main.ui
neil_vst_gui/main_worker.py
neil_vst_gui/play_chain.py
neil_vst_gui/rects_animate.py
neil_vst_gui/resources.py
neil_vst_gui/tag_write.py
neil_vst_gui/ui_logging.py
neil_vst_gui/ui_settings.py
neil_vst_gui-0.5.7.dist-info/LICENSE
neil_vst_gui-0.5.7.dist-info/METADATA
neil_vst_gui-0.5.7.dist-info/WHEEL
neil_vst_gui-0.5.7.dist-info/entry_points.txt
neil_vst_gui-0.5.7.dist-info/top_level.txt
neil_vst_gui-0.5.7.dist-info/RECORD
