Metadata-Version: 2.1
Name: neil-vst-gui
Version: 0.5.7
Summary: GUI application based on py-neil-vst package
Home-page: https://github.com/LeftRadio/py-neil-vst-gui
Author: Vladislav Kamenev
Author-email: vladislav@inorbit.com
License: MIT
Keywords: vst,plugin
Platform: UNKNOWN
Classifier: Development Status :: 4 - Beta
Classifier: Intended Audience :: Developers
Classifier: License :: OSI Approved :: MIT License
Classifier: Programming Language :: Python :: 3
Classifier: Programming Language :: Python :: 3.7
Classifier: Programming Language :: Python :: 3.8
Classifier: Programming Language :: Python :: 3.9
Requires-Dist: neil-vst (>=0.2.7)
Requires-Dist: SoundFile (>=0.10.3.post1)
Requires-Dist: sounddevice (>=0.4.2)
Requires-Dist: numpy (==1.19.0)
Requires-Dist: PyQt5
